clearskies_stripe/__init__.py
clearskies_stripe/backends/__init__.py
clearskies_stripe/backends/stripe_sdk_backend.py
clearskies_stripe/di/__init__.py
clearskies_stripe/di/stripe.py
clearskies_stripe/di/stripe_test.py
clearskies_stripe/exceptions/__init__.py
clearskies_stripe/exceptions/payment_failure.py
clearskies_stripe/handlers/__init__.py
clearskies_stripe/handlers/create_setup_intent.py
clearskies_stripe/handlers/create_setup_intent_test.py
clearskies_stripe/models/__init__.py
clearskies_stripe/models/column_types/__init__.py
clearskies_stripe/models/column_types/stripe_object.py
clearskies_stripe/models/stripe_charge.py
clearskies_stripe/models/stripe_customer.py
clearskies_stripe/models/stripe_payment_method.py
clear_skies_stripe-0.9.21.dist-info/LICENSE
clear_skies_stripe-0.9.21.dist-info/METADATA
clear_skies_stripe-0.9.21.dist-info/WHEEL
clear_skies_stripe-0.9.21.dist-info/RECORD
